pueblo/__init__.py
pueblo/cli.py
pueblo/context.py
pueblo/io/__init__.py
pueblo/io/universal.py
pueblo/ngr/README.md
pueblo/ngr/__init__.py
pueblo/ngr/cli.py
pueblo/ngr/core.py
pueblo/ngr/model.py
pueblo/ngr/runner.py
pueblo/ngr/util.py
pueblo/nlp/__init__.py
pueblo/nlp/resource.py
pueblo/rc/README.md
pueblo/rc/__init__.py
pueblo/sfa/README.md
pueblo/sfa/__init__.py
pueblo/sfa/cli.py
pueblo/sfa/core.py
pueblo/sfa/pep723.py
pueblo/testing/__init__.py
pueblo/testing/click.py
pueblo/testing/dataframe.py
pueblo/testing/folder.py
pueblo/testing/nlp.py
pueblo/testing/notebook.py
pueblo/testing/pandas.py
pueblo/testing/snippet.py
pueblo/util/__init__.py
pueblo/util/cli.py
pueblo/util/data.py
pueblo/util/environ.py
pueblo/util/fs.py
pueblo/util/logging.py
pueblo/util/proc.py
pueblo/util/program.py
pueblo-0.0.14.dist-info/licenses/LICENSE
pueblo-0.0.14.dist-info/METADATA
pueblo-0.0.14.dist-info/WHEEL
pueblo-0.0.14.dist-info/entry_points.txt
pueblo-0.0.14.dist-info/top_level.txt
pueblo-0.0.14.dist-info/RECORD
